{
  "86": {
    "edition": "86",
    "code": "WTNN",
    "imgs": [
      "W04",
      "T05",
      "N01",
      "N00"
    ]
  },
  "98": {
    "edition": "98",
    "code": "WTNN",
    "imgs": [
      "W11",
      "T13",
      "N01",
      "N00"
    ]
  },
  "word": "仡",
  "06": {
    "edition": "06",
    "code": "WTNN",
    "imgs": [
      "W11",
      "T13",
      "N01",
      "N00"
    ]
  },
  "pinyin": [
    "yì",
    "gē",
    "ㄧˋ",
    "ㄍㄜ"
  ],
  "audios": [
    "yì",
    "gē",
    "ㄧˋ",
    "ㄍㄜ"
  ]
}