{
  "86": {
    "edition": "86",
    "code": "UYIY",
    "imgs": [
      "U04",
      "Y06",
      "I08",
      "Y00"
    ]
  },
  "98": {
    "edition": "98",
    "code": "UYIY",
    "imgs": [
      "U02",
      "Y14",
      "I17",
      "Y00"
    ]
  },
  "word": "凉",
  "06": {
    "edition": "06",
    "code": "UYKI",
    "imgs": [
      "U02",
      "Y13",
      "K10",
      "I17"
    ]
  },
  "pinyin": [
    "liáng",
    "liàng",
    "ㄌㄧㄤˊ",
    "ㄌㄧㄤˋ"
  ],
  "audios": [
    "liáng",
    "liàng",
    "ㄌㄧㄤˊ",
    "ㄌㄧㄤˋ"
  ]
}