{
  "86": {
    "edition": "86",
    "code": "KMTY",
    "img": [
      "K01",
      "M02",
      "T01",
      "Y01"
    ]
  },
  "98": {
    "edition": "98",
    "code": "KMTY",
    "img": [
      "K10",
      "M14",
      "T01",
      "Y03"
    ]
  },
  "word": "吶",
  "06": {
    "edition": "06",
    "code": "KMTY",
    "img": [
      "K10",
      "M14",
      "T01",
      "Y03"
    ]
  },
  "pinyin": [
    "nà",
    "nè",
    "ㄋㄚˋ",
    "ㄋㄜˋ"
  ],
  "mp3": [
    "nà.mp3",
    "nè.mp3",
    "ㄋㄚˋ.mp3",
    "ㄋㄜˋ.mp3"
  ]
}