{
  "86": {
    "edition": "86",
    "code": "KTDK",
    "img": [
      "K01",
      "T01",
      "D01",
      "K01"
    ]
  },
  "98": {
    "edition": "98",
    "code": "KTDK",
    "img": [
      "K10",
      "T01",
      "D10",
      "K10"
    ]
  },
  "word": "嘺",
  "06": {
    "edition": "06",
    "code": "KTDK",
    "img": [
      "K10",
      "T01",
      "D10",
      "K10"
    ]
  },
  "pinyin": [
    "qiáo",
    "qiào",
    "ㄑㄧㄠˊ",
    "ㄑㄧㄠˋ"
  ],
  "mp3": [
    "qiáo.mp3",
    "qiào.mp3",
    "ㄑㄧㄠˊ.mp3",
    "ㄑㄧㄠˋ.mp3"
  ]
}