{
  "86": {
    "edition": "86",
    "code": "GKHE",
    "img": [
      "G01",
      "K01",
      "H01",
      "E10"
    ]
  },
  "98": {
    "edition": "98",
    "code": "GKHE",
    "img": [
      "G01",
      "K10",
      "H01",
      "E18"
    ]
  },
  "word": "囊",
  "06": {
    "edition": "06",
    "code": "GKHE",
    "img": [
      "G01",
      "K10",
      "H01",
      "E18"
    ]
  },
  "pinyin": [
    "náng",
    "nāng",
    "ㄋㄤˊ",
    "ㄋㄤ"
  ],
  "mp3": [
    "náng.mp3",
    "nāng.mp3",
    "ㄋㄤˊ.mp3",
    "ㄋㄤ.mp3"
  ]
}