{
  "86": {
    "edition": "86",
    "code": "VHJH",
    "imgs": [
      "V01",
      "H05",
      "J08",
      "H00"
    ]
  },
  "98": {
    "edition": "98",
    "code": "VHJH",
    "imgs": [
      "V10",
      "H17",
      "J15",
      "H00"
    ]
  },
  "word": "婥",
  "06": {
    "edition": "06",
    "code": "VHJF",
    "imgs": [
      "V10",
      "H17",
      "J10",
      "F13"
    ]
  },
  "pinyin": [
    "chuò",
    "nào",
    "ㄔㄨㄛˋ",
    "ㄋㄠˋ"
  ],
  "audios": [
    "chuò",
    "nào",
    "ㄔㄨㄛˋ",
    "ㄋㄠˋ"
  ]
}