{
  "86": {
    "edition": "86",
    "code": "NTKY",
    "imgs": [
      "N05",
      "T01",
      "K01",
      "Y12"
    ]
  },
  "98": {
    "edition": "98",
    "code": "NTKY",
    "imgs": [
      "N17",
      "T01",
      "K10",
      "Y01"
    ]
  },
  "word": "属",
  "06": {
    "edition": "06",
    "code": "NTKY",
    "imgs": [
      "N17",
      "T01",
      "K10",
      "Y01"
    ]
  },
  "pinyin": [
    "shǔ",
    "zhǔ",
    "ㄕㄨˇ",
    "ㄓㄨˇ"
  ],
  "audios": [
    "shǔ",
    "zhǔ",
    "ㄕㄨˇ",
    "ㄓㄨˇ"
  ]
}