{
  "86": {
    "edition": "86",
    "code": "FTFH",
    "imgs": [
      "F03",
      "T01",
      "F04",
      "H00"
    ]
  },
  "98": {
    "edition": "98",
    "code": "GDFH",
    "imgs": [
      "G01",
      "D17",
      "F12",
      "H00"
    ]
  },
  "word": "幵",
  "06": {
    "edition": "06",
    "code": "GDFH",
    "imgs": [
      "G01",
      "D17",
      "F12",
      "H00"
    ]
  },
  "pinyin": [
    "jiān",
    "qiān",
    "ㄐㄧㄢ",
    "ㄑㄧㄢ"
  ],
  "audios": [
    "jiān",
    "qiān",
    "ㄐㄧㄢ",
    "ㄑㄧㄢ"
  ]
}