{
  "86": {
    "edition": "86",
    "code": "XXDY",
    "imgs": [
      "X01",
      "X01",
      "D01",
      "Y12"
    ]
  },
  "98": {
    "edition": "98",
    "code": "XXAW",
    "imgs": [
      "X10",
      "X10",
      "A11",
      "W10"
    ]
  },
  "word": "幾",
  "06": {
    "edition": "06",
    "code": "XXDY",
    "imgs": [
      "X10",
      "X10",
      "D10",
      "Y01"
    ]
  },
  "pinyin": [
    "jī",
    "jǐ",
    "ㄐㄧ",
    "ㄐㄧˇ"
  ],
  "audios": [
    "jī",
    "jǐ",
    "ㄐㄧ",
    "ㄐㄧˇ"
  ]
}