{
  "86": {
    "edition": "86",
    "code": "XGLG",
    "imgs": [
      "X08",
      "G01",
      "L01",
      "G01"
    ]
  },
  "98": {
    "edition": "98",
    "code": "XGLG",
    "imgs": [
      "X14",
      "G01",
      "L10",
      "G01"
    ]
  },
  "word": "彊",
  "06": {
    "edition": "06",
    "code": "XGLG",
    "imgs": [
      "X14",
      "G01",
      "L10",
      "G01"
    ]
  },
  "pinyin": [
    "qiáng",
    "qiǎng",
    "jiàng",
    "ㄑㄧㄤˊ",
    "ㄑㄧㄤˇ",
    "ㄐㄧㄤˋ"
  ],
  "audios": [
    "qiáng",
    "qiǎng",
    "jiàng",
    "ㄑㄧㄤˊ",
    "ㄑㄧㄤˇ",
    "ㄐㄧㄤˋ"
  ]
}