{
  "86": {
    "edition": "86",
    "code": "TNHC",
    "imgs": [
      "T08",
      "N07",
      "H01",
      "C01"
    ]
  },
  "98": {
    "edition": "98",
    "code": "TNHC",
    "imgs": [
      "T14",
      "N15",
      "H01",
      "C10"
    ]
  },
  "word": "徦",
  "06": {
    "edition": "06",
    "code": "TNHC",
    "imgs": [
      "T14",
      "N15",
      "H01",
      "C10"
    ]
  },
  "pinyin": [
    "jiǎ",
    "xiá",
    "ㄐㄧㄚˇ",
    "ㄒㄧㄚˊ"
  ],
  "audios": [
    "jiǎ",
    "xiá",
    "ㄐㄧㄚˇ",
    "ㄒㄧㄚˊ"
  ]
}