{
  "86": {
    "edition": "86",
    "code": "SDAK",
    "imgs": [
      "S01",
      "D01",
      "A02",
      "K01"
    ]
  },
  "98": {
    "edition": "98",
    "code": "SDAK",
    "imgs": [
      "S10",
      "D10",
      "A17",
      "K10"
    ]
  },
  "word": "檶",
  "06": {
    "edition": "06",
    "code": "SDAK",
    "imgs": [
      "S10",
      "D10",
      "A17",
      "K10"
    ]
  },
  "pinyin": [
    "qiān",
    "lián",
    "ㄑㄧㄢ",
    "ㄌㄧㄢˊ"
  ],
  "audios": [
    "qiān",
    "lián",
    "ㄑㄧㄢ",
    "ㄌㄧㄢˊ"
  ]
}