{
  "86": {
    "edition": "86",
    "code": "IUOG",
    "imgs": [
      "I05",
      "U03",
      "O04",
      "G01"
    ]
  },
  "98": {
    "edition": "98",
    "code": "IUOG",
    "imgs": [
      "I01",
      "U12",
      "O19",
      "G00"
    ]
  },
  "word": "湴",
  "06": {
    "edition": "06",
    "code": "IUOG",
    "imgs": [
      "I01",
      "U12",
      "O11",
      "G01"
    ]
  },
  "pinyin": [
    "bàn",
    "pán",
    "ㄅㄢˋ",
    "ㄆㄢˊ"
  ],
  "audios": [
    "bàn",
    "pán",
    "ㄅㄢˋ",
    "ㄆㄢˊ"
  ]
}