{
  "86": {
    "edition": "86",
    "code": "WTLF",
    "imgs": [
      "W01",
      "T03",
      "L01",
      "F00"
    ]
  },
  "98": {
    "edition": "98",
    "code": "WGSL",
    "imgs": [
      "W10",
      "G01",
      "S15",
      "L10"
    ]
  },
  "word": "畬",
  "06": {
    "edition": "06",
    "code": "WGSL",
    "imgs": [
      "W10",
      "G01",
      "S10",
      "L10"
    ]
  },
  "pinyin": [
    "shē",
    "yú",
    "ㄕㄜ",
    "ㄩˊ"
  ],
  "audios": [
    "shē",
    "yú",
    "ㄕㄜ",
    "ㄩˊ"
  ]
}