{
  "86": {
    "edition": "86",
    "code": "UHKD",
    "imgs": [
      "U13",
      "H05",
      "K01",
      "D00"
    ]
  },
  "98": {
    "edition": "98",
    "code": "UHKD",
    "imgs": [
      "U20",
      "H17",
      "K10",
      "D00"
    ]
  },
  "word": "痁",
  "06": {
    "edition": "06",
    "code": "UHKD",
    "imgs": [
      "U20",
      "H17",
      "K10",
      "D00"
    ]
  },
  "pinyin": [
    "shān",
    "diàn",
    "ㄕㄢ",
    "ㄉㄧㄢˋ"
  ],
  "audios": [
    "shān",
    "diàn",
    "ㄕㄢ",
    "ㄉㄧㄢˋ"
  ]
}