{
  "86": {
    "edition": "86",
    "code": "DXJH",
    "img": [
      "D12",
      "X08",
      "J06",
      "H00"
    ]
  },
  "98": {
    "edition": "98",
    "code": "DXJH",
    "img": [
      "D14",
      "X14",
      "J04",
      "H00"
    ]
  },
  "word": "砩",
  "06": {
    "edition": "06",
    "code": "DXJH",
    "img": [
      "D14",
      "X14",
      "J04",
      "H00"
    ]
  },
  "pinyin": [
    "fú",
    "fèi",
    "ㄈㄨˊ",
    "ㄈㄟˋ"
  ],
  "mp3": [
    "fú.mp3",
    "fèi.mp3",
    "ㄈㄨˊ.mp3",
    "ㄈㄟˋ.mp3"
  ]
}