{
  "86": {
    "edition": "86",
    "code": "XFFG",
    "imgs": [
      "X05",
      "F01",
      "F01",
      "G00"
    ]
  },
  "98": {
    "edition": "98",
    "code": "XFFG",
    "imgs": [
      "X13",
      "F10",
      "F10",
      "G00"
    ]
  },
  "word": "絓",
  "06": {
    "edition": "06",
    "code": "XFFG",
    "imgs": [
      "X13",
      "F10",
      "F10",
      "G00"
    ]
  },
  "pinyin": [
    "guà",
    "kuā",
    "ㄍㄨㄚˋ",
    "ㄎㄨㄚ"
  ],
  "audios": [
    "guà",
    "kuā",
    "ㄍㄨㄚˋ",
    "ㄎㄨㄚ"
  ]
}