{
  "86": {
    "edition": "86",
    "code": "XMEE",
    "imgs": [
      "X05",
      "M01",
      "E01",
      "E01"
    ]
  },
  "98": {
    "edition": "98",
    "code": "XMEE",
    "imgs": [
      "X13",
      "M10",
      "E10",
      "E10"
    ]
  },
  "word": "繃",
  "06": {
    "edition": "06",
    "code": "XMEE",
    "imgs": [
      "X13",
      "M10",
      "E10",
      "E10"
    ]
  },
  "pinyin": [
    "bēng",
    "běng",
    "bèng",
    "ㄅㄥ",
    "ㄅㄥˇ",
    "ㄅㄥˋ"
  ],
  "audios": [
    "bēng",
    "běng",
    "bèng",
    "ㄅㄥ",
    "ㄅㄥˇ",
    "ㄅㄥˋ"
  ]
}