{
  "86": {
    "edition": "86",
    "code": "DUDJ",
    "img": [
      "D01",
      "U02",
      "D04",
      "J00"
    ]
  },
  "98": {
    "edition": "98",
    "code": "DUJ",
    "img": [
      "D10",
      "U41",
      "J00"
    ]
  },
  "word": "羍",
  "06": {
    "edition": "06",
    "code": "DUGJ",
    "img": [
      "D10",
      "U12",
      "G13",
      "J00"
    ]
  },
  "pinyin": [
    "dá",
    "xìng",
    "ㄉㄚˊ",
    "ㄒㄧㄥˋ"
  ],
  "mp3": [
    "dá.mp3",
    "xìng.mp3",
    "ㄉㄚˊ.mp3",
    "ㄒㄧㄥˋ.mp3"
  ]
}