{
  "86": {
    "edition": "86",
    "code": "DMJD",
    "img": [
      "D10",
      "M02",
      "J04",
      "D01"
    ]
  },
  "98": {
    "edition": "98",
    "code": "DMJD",
    "img": [
      "D16",
      "M14",
      "J01",
      "D10"
    ]
  },
  "word": "耎",
  "06": {
    "edition": "06",
    "code": "DMJD",
    "img": [
      "D16",
      "M14",
      "J01",
      "D10"
    ]
  },
  "pinyin": [
    "ruǎn",
    "nuò",
    "ㄖㄨㄢˇ",
    "ㄋㄨㄛˋ"
  ],
  "mp3": [
    "ruǎn.mp3",
    "nuò.mp3",
    "ㄖㄨㄢˇ.mp3",
    "ㄋㄨㄛˋ.mp3"
  ]
}