{
  "86": {
    "edition": "86",
    "code": "AUVF",
    "imgs": [
      "A05",
      "U01",
      "V01",
      "F00"
    ]
  },
  "98": {
    "edition": "98",
    "code": "AUVF",
    "imgs": [
      "A12",
      "U10",
      "V10",
      "F00"
    ]
  },
  "word": "菨",
  "06": {
    "edition": "06",
    "code": "AUVF",
    "imgs": [
      "A12",
      "U10",
      "V10",
      "F00"
    ]
  },
  "pinyin": [
    "jiē",
    "shà",
    "ㄐㄧㄝ",
    "ㄕㄚˋ"
  ],
  "audios": [
    "jiē",
    "shà",
    "ㄐㄧㄝ",
    "ㄕㄚˋ"
  ]
}