{
  "86": {
    "edition": "86",
    "code": "YHIC",
    "imgs": [
      "Y04",
      "H04",
      "I08",
      "C01"
    ]
  },
  "98": {
    "edition": "98",
    "code": "YHIC",
    "imgs": [
      "Y12",
      "H12",
      "I17",
      "C10"
    ]
  },
  "word": "諔",
  "06": {
    "edition": "06",
    "code": "YHGC",
    "imgs": [
      "Y12",
      "H17",
      "G01",
      "C10"
    ]
  },
  "pinyin": [
    "chù",
    "jí",
    "ㄔㄨˋ",
    "ㄐㄧˊ"
  ],
  "audios": [
    "chù",
    "jí",
    "ㄔㄨˋ",
    "ㄐㄧˊ"
  ]
}