{
  "86": {
    "edition": "86",
    "code": "LUQY",
    "imgs": [
      "L11",
      "U10",
      "Q07",
      "Y00"
    ]
  },
  "98": {
    "edition": "98",
    "code": "LURY",
    "imgs": [
      "L18",
      "U16",
      "R85",
      "Y00"
    ]
  },
  "word": "较",
  "06": {
    "edition": "06",
    "code": "LYWR",
    "imgs": [
      "L18",
      "Y13",
      "W13",
      "R85"
    ]
  },
  "pinyin": [
    "jiào",
    "jué",
    "ㄐㄧㄠˋ",
    "ㄐㄩㄝˊ"
  ],
  "audios": [
    "jiào",
    "jué",
    "ㄐㄧㄠˋ",
    "ㄐㄩㄝˊ"
  ]
}