{
  "86": {
    "edition": "86",
    "code": "FTJB",
    "img": [
      "F01",
      "T01",
      "J01",
      "B04"
    ]
  },
  "98": {
    "edition": "98",
    "code": "FTJB",
    "img": [
      "F10",
      "T01",
      "J10",
      "B12"
    ]
  },
  "word": "都",
  "06": {
    "edition": "06",
    "code": "FTJB",
    "img": [
      "F10",
      "T01",
      "J10",
      "B12"
    ]
  },
  "pinyin": [
    "dū",
    "dōu",
    "ㄉㄨ",
    "ㄉㄡ"
  ],
  "mp3": [
    "dū.mp3",
    "dōu.mp3",
    "ㄉㄨ.mp3",
    "ㄉㄡ.mp3"
  ]
}