{
  "86": {
    "edition": "86",
    "code": "QTLX",
    "imgs": [
      "Q03",
      "T01",
      "L10",
      "X11"
    ]
  },
  "98": {
    "edition": "98",
    "code": "QTLX",
    "imgs": [
      "Q12",
      "T01",
      "L12",
      "X17"
    ]
  },
  "word": "鎞",
  "06": {
    "edition": "06",
    "code": "QTLX",
    "imgs": [
      "Q12",
      "T01",
      "L12",
      "X17"
    ]
  },
  "pinyin": [
    "bī",
    "bì",
    "pī",
    "ㄅㄧ",
    "ㄅㄧˋ",
    "ㄆㄧ"
  ],
  "audios": [
    "bī",
    "bì",
    "pī",
    "ㄅㄧ",
    "ㄅㄧˋ",
    "ㄆㄧ"
  ]
}