{
  "86": {
    "edition": "86",
    "code": "AKKY",
    "img": [
      "A05",
      "K01",
      "K01",
      "Y07"
    ]
  },
  "98": {
    "edition": "98",
    "code": "AKKY",
    "img": [
      "A12",
      "K10",
      "K10",
      "Y17"
    ]
  },
  "word": "雚",
  "06": {
    "edition": "06",
    "code": "AKKY",
    "img": [
      "A12",
      "K10",
      "K10",
      "Y17"
    ]
  },
  "pinyin": [
    "guàn",
    "huán",
    "ㄍㄨㄢˋ",
    "ㄏㄨㄢˊ"
  ],
  "mp3": [
    "guàn.mp3",
    "huán.mp3",
    "ㄍㄨㄢˋ.mp3",
    "ㄏㄨㄢˊ.mp3"
  ]
}