{
  "86": {
    "edition": "86",
    "code": "YNJT",
    "imgs": [
      "Y11",
      "N07",
      "J04",
      "T02"
    ]
  },
  "98": {
    "edition": "98",
    "code": "OXXT",
    "imgs": [
      "O18",
      "X18",
      "X17",
      "T10"
    ]
  },
  "word": "麇",
  "06": {
    "edition": "06",
    "code": "ONJT",
    "imgs": [
      "O16",
      "N15",
      "J01",
      "T10"
    ]
  },
  "pinyin": [
    "jūn",
    "qún",
    "ㄐㄩㄣ",
    "ㄑㄩㄣˊ"
  ],
  "audios": [
    "jūn",
    "qún",
    "ㄐㄩㄣ",
    "ㄑㄩㄣˊ"
  ]
}